main/Inter.ttf
main/__init__.py
main/ai_backend.py
main/chatter.py
main/config.json
main/main.py
main/tts.py
main/voice_recognition.py
main/models/UK/en_GB-northern_english_male-medium.onnx
main/models/UK/en_GB-northern_english_male-medium.onnx.json
project_chatter-0.2.2.dist-info/licenses/LICENSE
project_chatter-0.2.2.dist-info/METADATA
project_chatter-0.2.2.dist-info/WHEEL
project_chatter-0.2.2.dist-info/entry_points.txt
project_chatter-0.2.2.dist-info/top_level.txt
project_chatter-0.2.2.dist-info/RECORD
