Metadata-Version: 2.4
Name: project-chatter
Version: 0.2.2
Summary: Chatter — AI Voice Assistant with Pygame UI
Home-page: https://github.com/divpreeet/project-chatter
Author: Divpreet Singh
Author-email: ytbraced@gmail.com
Classifier: Programming Language :: Python :: 3
Classifier: Operating System :: OS Independent
Classifier: Topic :: Multimedia :: Sound/Audio
Requires-Python: >=3.7
License-File: LICENSE
Requires-Dist: altgraph==0.17.4
Requires-Dist: annotated-types==0.7.0
Requires-Dist: anyio==4.9.0
Requires-Dist: arrow==1.3.0
Requires-Dist: attmap==0.13.2
Requires-Dist: attrs==25.3.0
Requires-Dist: binaryornot==0.4.4
Requires-Dist: briefcase==0.3.23
Requires-Dist: build==1.2.2.post1
Requires-Dist: certifi==2025.4.26
Requires-Dist: cffi==1.17.1
Requires-Dist: chardet==5.2.0
Requires-Dist: charset-normalizer==3.4.2
Requires-Dist: click==8.2.1
Requires-Dist: coloredlogs==15.0.1
Requires-Dist: cookiecutter==2.6.0
Requires-Dist: dmgbuild==1.6.5
Requires-Dist: ds-store==1.3.1
Requires-Dist: eido==0.2.4
Requires-Dist: flatbuffers==25.2.10
Requires-Dist: gitdb==4.0.12
Requires-Dist: GitPython==3.1.44
Requires-Dist: h11==0.16.0
Requires-Dist: httpcore==1.0.9
Requires-Dist: httpx==0.28.1
Requires-Dist: humanfriendly==10.0
Requires-Dist: idna==3.10
Requires-Dist: Jinja2==3.1.6
Requires-Dist: jsonschema==4.24.0
Requires-Dist: jsonschema-specifications==2025.4.1
Requires-Dist: logmuse==0.2.8
Requires-Dist: mac-alias==2.2.2
Requires-Dist: macholib==1.16.3
Requires-Dist: markdown-it-py==3.0.0
Requires-Dist: MarkupSafe==3.0.2
Requires-Dist: mdurl==0.1.2
Requires-Dist: mpmath==1.3.0
Requires-Dist: numpy==2.3.0
Requires-Dist: onnxruntime==1.19.2
Requires-Dist: oyaml==1.0
Requires-Dist: packaging==25.0
Requires-Dist: pandas==2.3.0
Requires-Dist: pephubclient==0.4.5
Requires-Dist: peppy==0.40.7
Requires-Dist: piper==0.14.4
Requires-Dist: pipestat==0.12.1
Requires-Dist: platformdirs==4.3.8
Requires-Dist: protobuf==6.31.1
Requires-Dist: psutil==7.0.0
Requires-Dist: PyAudio==0.2.14
Requires-Dist: pycparser==2.22
Requires-Dist: pydantic==2.11.5
Requires-Dist: pydantic_core==2.33.2
Requires-Dist: pygame==2.6.1
Requires-Dist: Pygments==2.19.1
Requires-Dist: pyinstaller-hooks-contrib==2025.4
Requires-Dist: pyproject_hooks==1.2.0
Requires-Dist: python-dateutil==2.9.0.post0
Requires-Dist: python-slugify==8.0.4
Requires-Dist: pytz==2025.2
Requires-Dist: PyYAML==6.0.2
Requires-Dist: referencing==0.36.2
Requires-Dist: requests==2.32.3
Requires-Dist: rich==14.0.0
Requires-Dist: rpds-py==0.25.1
Requires-Dist: shellingham==1.5.4
Requires-Dist: six==1.17.0
Requires-Dist: smmap==5.0.2
Requires-Dist: sniffio==1.3.1
Requires-Dist: sounddevice==0.5.2
Requires-Dist: SpeechRecognition==3.14.3
Requires-Dist: sympy==1.14.0
Requires-Dist: text-unidecode==1.3
Requires-Dist: tomli_w==1.2.0
Requires-Dist: typer==0.16.0
Requires-Dist: types-python-dateutil==2.9.0.20250516
Requires-Dist: typing-inspection==0.4.1
Requires-Dist: typing_extensions==4.14.0
Requires-Dist: tzdata==2025.2
Requires-Dist: ubiquerg==0.8.1
Requires-Dist: urllib3==2.4.0
Requires-Dist: yacman==0.9.3
Provides-Extra: voice
Requires-Dist: piper-phonemize-cross>=1.2.1; extra == "voice"
Requires-Dist: piper-tts==1.2.0; extra == "voice"
Dynamic: author
Dynamic: author-email
Dynamic: classifier
Dynamic: description
Dynamic: description-content-type
Dynamic: home-page
Dynamic: license-file
Dynamic: provides-extra
Dynamic: requires-dist
Dynamic: requires-python
Dynamic: summary
